pallets/__init__.py
pallets/__main__.py
pallets/color.py
pallets/columnpanelui.py
pallets/consoleschemerenderer.py
pallets/css.py
pallets/namegenerator.py
pallets/scheme.py
pallets/schemegenerator.py
pallets/resources/adjectives.txt
pallets/resources/nouns.txt
pallets-0.1.1.dist-info/LICENSE
pallets-0.1.1.dist-info/METADATA
pallets-0.1.1.dist-info/WHEEL
pallets-0.1.1.dist-info/entry_points.txt
pallets-0.1.1.dist-info/top_level.txt
pallets-0.1.1.dist-info/RECORD
