Metadata-Version: 2.1
Name: pallets
Version: 0.1.1
Summary: Generate color palletes on the command line
Author-email: Emil Kloeden <emilkloeden@gmail.com>
License: MIT License        
Project-URL: Homepage, https://emilkloeden.github.io/pallets
Project-URL: Github, https://github.com/emilkloeden/pallets
Keywords: color,color scheme,color pallet,pallet,color pallete,colour
Classifier: License :: OSI Approved :: MIT License
Classifier: Programming Language :: Python
Classifier: Programming Language :: Python :: 3
Requires-Python: >=3.9
License-File: LICENSE
Requires-Dist: rich (==12.4.4)
Requires-Dist: importlib-resources ; python_version < "3.9"
Provides-Extra: dev
Requires-Dist: black ; extra == 'dev'
Requires-Dist: bumpver ; extra == 'dev'
Requires-Dist: isort ; extra == 'dev'
Requires-Dist: pip-tools ; extra == 'dev'
Requires-Dist: pytest ; extra == 'dev'
